scraperwiki/__init__.py
scraperwiki/utils.py
scraperwiki/sql.py
scraperwiki-0.5.dist-info/WHEEL
scraperwiki-0.5.dist-info/METADATA
scraperwiki-0.5.dist-info/DESCRIPTION.rst
scraperwiki-0.5.dist-info/metadata.json
scraperwiki-0.5.dist-info/top_level.txt
scraperwiki-0.5.dist-info/RECORD
