Metadata-Version: 2.0
Name: scraperwiki
Version: 0.5
Summary: Local version of ScraperWiki libraries
Home-page: https://github.com/scraperwiki/scraperwiki-python
Author: Francis Irving
Author-email: francis@scraperwiki.com
License: GPL
Platform: UNKNOWN
Classifier: Intended Audience :: Developers
Classifier: Intended Audience :: Science/Research
Classifier: License :: OSI Approved :: GNU General Public License v3 or later (GPLv3+)
Classifier: Programming Language :: Python :: 2.7
Classifier: Programming Language :: Python :: 3.4
Classifier: Programming Language :: SQL
Classifier: Topic :: Database :: Front-Ends
Requires-Dist: requests
Requires-Dist: six
Requires-Dist: sqlalchemy
Requires-Dist: alembic
